{
 "custom_fields": [
  {
   "_assign": null, 
   "_comments": null, 
   "_liked_by": null, 
   "_user_tags": null, 
   "allow_on_submit": 0, 
   "bold": 0, 
   "collapsible": 0, 
   "collapsible_depends_on": null, 
   "columns": 0, 
   "creation": "2018-10-29 10:10:56.576204", 
   "default": null, 
   "depends_on": null, 
   "description": null, 
   "docstatus": 0, 
   "dt": "Address", 
   "fieldname": "posta", 
   "fieldtype": "Link", 
   "hidden": 0, 
   "idx": 6, 
   "ignore_user_permissions": 0, 
   "ignore_xss_filter": 0, 
   "in_filter": 0, 
   "in_filter_dash": 0, 
   "in_global_search": 0, 
   "in_list_view": 0, 
   "in_standard_filter": 0, 
   "insert_after": "address_line2", 
   "label": "Posta", 
   "modified": "2016-11-03 23:09:22.899426", 
   "modified_by": "Administrator", 
   "name": "Address-posta", 
   "no_copy": 0, 
   "options": "Postne Stevilke", 
   "owner": "Administrator", 
   "parent": null, 
   "parentfield": null, 
   "parenttype": null, 
   "permlevel": 0, 
   "precision": "", 
   "print_hide": 0, 
   "print_hide_if_no_value": 0, 
   "print_width": null, 
   "read_only": 0, 
   "report_hide": 0, 
   "reqd": 0, 
   "search_index": 0, 
   "translatable": 1, 
   "unique": 0, 
   "width": null
  }
 ], 
 "custom_perms": [], 
 "doctype": "Address", 
 "property_setters": [
  {
   "_assign": null, 
   "_comments": null, 
   "_liked_by": null, 
   "_user_tags": null, 
   "creation": "2018-10-31 07:09:23.326715", 
   "default_value": null, 
   "doc_type": "Address", 
   "docstatus": 0, 
   "doctype_or_field": "DocField", 
   "field_name": "fax", 
   "idx": 0, 
   "modified": "2018-10-31 07:09:23.326715", 
   "modified_by": "Administrator", 
   "name": "Address-fax-hidden", 
   "owner": "Administrator", 
   "parent": null, 
   "parentfield": null, 
   "parenttype": null, 
   "property": "hidden", 
   "property_type": "Check", 
   "value": "1"
  }, 
  {
   "_assign": null, 
   "_comments": null, 
   "_liked_by": null, 
   "_user_tags": null, 
   "creation": "2018-10-31 07:09:23.143544", 
   "default_value": null, 
   "doc_type": "Address", 
   "docstatus": 0, 
   "doctype_or_field": "DocType", 
   "field_name": null, 
   "idx": 0, 
   "modified": "2018-10-31 07:09:23.143544", 
   "modified_by": "Administrator", 
   "name": "Address-read_only_onload", 
   "owner": "Administrator", 
   "parent": null, 
   "parentfield": null, 
   "parenttype": null, 
   "property": "read_only_onload", 
   "property_type": "Check", 
   "value": null
  }, 
  {
   "_assign": null, 
   "_comments": null, 
   "_liked_by": null, 
   "_user_tags": null, 
   "creation": "2018-10-30 21:47:51.430613", 
   "default_value": null, 
   "doc_type": "Address", 
   "docstatus": 0, 
   "doctype_or_field": "DocField", 
   "field_name": "county", 
   "idx": 0, 
   "modified": "2018-10-30 21:47:51.430613", 
   "modified_by": "Administrator", 
   "name": "Address-county-depends_on", 
   "owner": "Administrator", 
   "parent": null, 
   "parentfield": null, 
   "parenttype": null, 
   "property": "depends_on", 
   "property_type": "Data", 
   "value": "eval:doc.country!= \"Slovenia\""
  }, 
  {
   "_assign": null, 
   "_comments": null, 
   "_liked_by": null, 
   "_user_tags": null, 
   "creation": "2018-10-30 21:47:15.124564", 
   "default_value": null, 
   "doc_type": "Address", 
   "docstatus": 0, 
   "doctype_or_field": "DocField", 
   "field_name": "state", 
   "idx": 0, 
   "modified": "2018-10-30 21:47:15.124564", 
   "modified_by": "Administrator", 
   "name": "Address-state-depends_on", 
   "owner": "Administrator", 
   "parent": null, 
   "parentfield": null, 
   "parenttype": null, 
   "property": "depends_on", 
   "property_type": "Data", 
   "value": "eval:doc.country!= \"Slovenia\""
  }, 
  {
   "_assign": null, 
   "_comments": null, 
   "_liked_by": null, 
   "_user_tags": null, 
   "creation": "2018-04-24 10:10:00.410922", 
   "default_value": null, 
   "doc_type": "Address", 
   "docstatus": 0, 
   "doctype_or_field": "DocField", 
   "field_name": "address_line2", 
   "idx": 0, 
   "modified": "2018-04-24 10:10:00.410922", 
   "modified_by": null, 
   "name": "Address-address_line2-translatable", 
   "owner": null, 
   "parent": null, 
   "parentfield": null, 
   "parenttype": null, 
   "property": "translatable", 
   "property_type": null, 
   "value": "1"
  }, 
  {
   "_assign": null, 
   "_comments": null, 
   "_liked_by": null, 
   "_user_tags": null, 
   "creation": "2018-04-24 10:10:00.406192", 
   "default_value": null, 
   "doc_type": "Address", 
   "docstatus": 0, 
   "doctype_or_field": "DocField", 
   "field_name": "address_line1", 
   "idx": 0, 
   "modified": "2018-04-24 10:10:00.406192", 
   "modified_by": null, 
   "name": "Address-address_line1-translatable", 
   "owner": null, 
   "parent": null, 
   "parentfield": null, 
   "parenttype": null, 
   "property": "translatable", 
   "property_type": null, 
   "value": "1"
  }
 ], 
 "sync_on_migrate": 1
}